gziputil.py
ioutil.py
reutil.py
tarutil.py
version.py
cnudie/__init__.py
cnudie/access.py
cnudie/purge.py
cnudie/retrieve.py
cnudie/retrieve_async.py
cnudie/util.py
ctt/README
ctt/__init__.py
ctt/__main__.py
ctt/filters.py
ctt/model.py
ctt/oci_platform.py
ctt/oci_util.py
ctt/process_dependencies.py
ctt/processors.py
ctt/replicate.py
ctt/simple-cfg
ctt/targets.py
ctt/uploaders.py
ctt/util.py
ocm/VERSION
ocm/__init__.py
ocm/__main__.py
ocm/base_component.py
ocm/branch_info.py
ocm/gardener.py
ocm/helm.py
ocm/iter.py
ocm/iter_async.py
ocm/oci.py
ocm/ocm-component-descriptor-schema.yaml
ocm/sign.py
ocm/upload.py
ocm/util.py
ocm/validate.py
gardener_ocm-1.2740.0.dist-info/LICENSE
gardener_ocm-1.2740.0.dist-info/METADATA
gardener_ocm-1.2740.0.dist-info/WHEEL
gardener_ocm-1.2740.0.dist-info/entry_points.txt
gardener_ocm-1.2740.0.dist-info/top_level.txt
gardener_ocm-1.2740.0.dist-info/RECORD
