Metadata-Version: 2.1
Name: gardener-ocm
Version: 1.2740.0
Summary: Open-Component-Model (OCM) language bindings
Requires-Python: >=3.11
License-File: LICENSE
Requires-Dist: PyYaml
Requires-Dist: cachetools
Requires-Dist: dacite
Requires-Dist: gardener-oci
Requires-Dist: jsonschema
Requires-Dist: python-dateutil
Requires-Dist: semver
